{
  "schema_version": "qcp-timing-summary/v2",
  "run_id": "xizi_double_link_init-20260714180003",
  "time_format": "UTC ISO-8601",
  "nodes": [
    {
      "sequence": 1,
      "event": "controller-command-start",
      "node_type": "start",
      "timestamp": "2026-07-14T09:53:08.971583Z",
      "category": "controller_command",
      "name": "init-run",
      "phase": "intake",
      "round": null,
      "group": null,
      "attempt": null,
      "timer_key": "controller_command:init-run"
    },
    {
      "sequence": 2,
      "event": "run-start",
      "node_type": "start",
      "timestamp": "2026-07-14T09:53:08.971583Z",
      "category": "run",
      "name": "xizi_double_link_init-20260714180003",
      "phase": "intake",
      "round": null,
      "group": null,
      "attempt": null,
      "timer_key": "run:xizi_double_link_init-20260714180003"
    },
    {
      "sequence": 3,
      "event": "phase-start",
      "node_type": "start",
      "timestamp": "2026-07-14T09:53:08.971583Z",
      "category": "phase",
      "name": "intake",
      "phase": "intake",
      "round": null,
      "group": null,
      "attempt": null,
      "timer_key": "phase:intake"
    },
    {
      "sequence": 4,
      "event": "controller-command-end",
      "node_type": "end",
      "timestamp": "2026-07-14T09:53:08.976416Z",
      "category": "controller_command",
      "name": "init-run",
      "phase": "intake",
      "round": null,
      "group": null,
      "attempt": null,
      "timer_key": "controller_command:init-run",
      "duration_seconds": 0.004833,
      "paired_start_sequence": 1
    },
    {
      "sequence": 5,
      "event": "controller-command-start",
      "node_type": "start",
      "timestamp": "2026-07-14T09:53:21.482870Z",
      "category": "controller_command",
      "name": "step",
      "phase": "intake",
      "round": null,
      "group": null,
      "attempt": null,
      "timer_key": "controller_command:step"
    },
    {
      "sequence": 6,
      "event": "phase-end",
      "node_type": "end",
      "timestamp": "2026-07-14T09:53:22.741074Z",
      "category": "phase",
      "name": "intake",
      "phase": "intake",
      "round": null,
      "group": null,
      "attempt": null,
      "timer_key": "phase:intake",
      "duration_seconds": 13.769491,
      "paired_start_sequence": 3
    },
    {
      "sequence": 7,
      "event": "phase-start",
      "node_type": "start",
      "timestamp": "2026-07-14T09:53:22.741074Z",
      "category": "phase",
      "name": "annotation",
      "phase": "annotation",
      "round": null,
      "group": null,
      "attempt": null,
      "timer_key": "phase:annotation"
    },
    {
      "sequence": 8,
      "event": "controller-command-end",
      "node_type": "end",
      "timestamp": "2026-07-14T09:53:22.755497Z",
      "category": "controller_command",
      "name": "step",
      "phase": "annotation",
      "round": null,
      "group": null,
      "attempt": null,
      "timer_key": "controller_command:step",
      "duration_seconds": 1.272627,
      "paired_start_sequence": 5
    },
    {
      "sequence": 9,
      "event": "controller-command-start",
      "node_type": "start",
      "timestamp": "2026-07-14T09:53:28.947690Z",
      "category": "controller_command",
      "name": "spawn-instructions",
      "phase": "annotation",
      "round": null,
      "group": null,
      "attempt": null,
      "timer_key": "controller_command:spawn-instructions"
    },
    {
      "sequence": 10,
      "event": "controller-command-end",
      "node_type": "end",
      "timestamp": "2026-07-14T09:53:28.949302Z",
      "category": "controller_command",
      "name": "spawn-instructions",
      "phase": "annotation",
      "round": null,
      "group": null,
      "attempt": null,
      "timer_key": "controller_command:spawn-instructions",
      "duration_seconds": 0.001612,
      "paired_start_sequence": 9
    },
    {
      "sequence": 11,
      "event": "controller-command-start",
      "node_type": "start",
      "timestamp": "2026-07-14T09:54:11.110622Z",
      "category": "controller_command",
      "name": "mark-attempt-started",
      "phase": "annotation",
      "round": null,
      "group": null,
      "attempt": null,
      "timer_key": "controller_command:mark-attempt-started"
    },
    {
      "sequence": 12,
      "event": "attempt-start",
      "node_type": "start",
      "timestamp": "2026-07-14T09:54:11.111305Z",
      "category": "attempt",
      "name": "xizi_double_link_init-annotation-r1-attempt-1",
      "phase": "annotation",
      "round": "xizi_double_link_init-annotation-r1",
      "group": null,
      "attempt": "xizi_double_link_init-annotation-r1-attempt-1",
      "timer_key": "attempt:xizi_double_link_init-annotation-r1-attempt-1"
    },
    {
      "sequence": 13,
      "event": "controller-command-end",
      "node_type": "end",
      "timestamp": "2026-07-14T09:54:11.113160Z",
      "category": "controller_command",
      "name": "mark-attempt-started",
      "phase": "annotation",
      "round": null,
      "group": null,
      "attempt": null,
      "timer_key": "controller_command:mark-attempt-started",
      "duration_seconds": 0.002538,
      "paired_start_sequence": 11
    },
    {
      "sequence": 14,
      "event": "controller-command-start",
      "node_type": "start",
      "timestamp": "2026-07-14T10:08:59.125529Z",
      "category": "controller_command",
      "name": "mark-attempt-returned",
      "phase": "annotation",
      "round": null,
      "group": null,
      "attempt": null,
      "timer_key": "controller_command:mark-attempt-returned"
    },
    {
      "sequence": 15,
      "event": "attempt-end",
      "node_type": "end",
      "timestamp": "2026-07-14T10:08:59.126155Z",
      "category": "attempt",
      "name": "xizi_double_link_init-annotation-r1-attempt-1",
      "phase": "annotation",
      "round": "xizi_double_link_init-annotation-r1",
      "group": null,
      "attempt": "xizi_double_link_init-annotation-r1-attempt-1",
      "timer_key": "attempt:xizi_double_link_init-annotation-r1-attempt-1",
      "duration_seconds": 888.01485,
      "paired_start_sequence": 12
    },
    {
      "sequence": 16,
      "event": "controller-command-end",
      "node_type": "end",
      "timestamp": "2026-07-14T10:08:59.128076Z",
      "category": "controller_command",
      "name": "mark-attempt-returned",
      "phase": "annotation",
      "round": null,
      "group": null,
      "attempt": null,
      "timer_key": "controller_command:mark-attempt-returned",
      "duration_seconds": 0.002547,
      "paired_start_sequence": 14
    },
    {
      "sequence": 17,
      "event": "controller-command-start",
      "node_type": "start",
      "timestamp": "2026-07-14T10:08:59.237399Z",
      "category": "controller_command",
      "name": "review-attempt",
      "phase": "annotation",
      "round": null,
      "group": null,
      "attempt": null,
      "timer_key": "controller_command:review-attempt"
    },
    {
      "sequence": 18,
      "event": "controller-command-end",
      "node_type": "end",
      "timestamp": "2026-07-14T10:08:59.240270Z",
      "category": "controller_command",
      "name": "review-attempt",
      "phase": "annotation",
      "round": null,
      "group": null,
      "attempt": null,
      "timer_key": "controller_command:review-attempt",
      "duration_seconds": 0.002871,
      "paired_start_sequence": 17
    },
    {
      "sequence": 19,
      "event": "controller-command-start",
      "node_type": "start",
      "timestamp": "2026-07-14T10:09:08.220487Z",
      "category": "controller_command",
      "name": "retry-round",
      "phase": "annotation",
      "round": null,
      "group": null,
      "attempt": null,
      "timer_key": "controller_command:retry-round"
    },
    {
      "sequence": 20,
      "event": "controller-command-end",
      "node_type": "end",
      "timestamp": "2026-07-14T10:09:08.221541Z",
      "category": "controller_command",
      "name": "retry-round",
      "phase": "annotation",
      "round": null,
      "group": null,
      "attempt": null,
      "timer_key": "controller_command:retry-round",
      "duration_seconds": 0.001054,
      "paired_start_sequence": 19
    },
    {
      "sequence": 21,
      "event": "controller-command-start",
      "node_type": "start",
      "timestamp": "2026-07-14T10:09:13.750426Z",
      "category": "controller_command",
      "name": "retry-round",
      "phase": "annotation",
      "round": null,
      "group": null,
      "attempt": null,
      "timer_key": "controller_command:retry-round"
    },
    {
      "sequence": 22,
      "event": "controller-command-end",
      "node_type": "end",
      "timestamp": "2026-07-14T10:09:15.063965Z",
      "category": "controller_command",
      "name": "retry-round",
      "phase": "annotation",
      "round": null,
      "group": null,
      "attempt": null,
      "timer_key": "controller_command:retry-round",
      "duration_seconds": 1.313539,
      "paired_start_sequence": 21
    },
    {
      "sequence": 23,
      "event": "controller-command-start",
      "node_type": "start",
      "timestamp": "2026-07-14T10:09:19.434650Z",
      "category": "controller_command",
      "name": "spawn-instructions",
      "phase": "annotation",
      "round": null,
      "group": null,
      "attempt": null,
      "timer_key": "controller_command:spawn-instructions"
    },
    {
      "sequence": 24,
      "event": "controller-command-end",
      "node_type": "end",
      "timestamp": "2026-07-14T10:09:19.436613Z",
      "category": "controller_command",
      "name": "spawn-instructions",
      "phase": "annotation",
      "round": null,
      "group": null,
      "attempt": null,
      "timer_key": "controller_command:spawn-instructions",
      "duration_seconds": 0.001963,
      "paired_start_sequence": 23
    },
    {
      "sequence": 25,
      "event": "controller-command-start",
      "node_type": "start",
      "timestamp": "2026-07-14T10:09:39.830814Z",
      "category": "controller_command",
      "name": "mark-attempt-started",
      "phase": "annotation",
      "round": null,
      "group": null,
      "attempt": null,
      "timer_key": "controller_command:mark-attempt-started"
    },
    {
      "sequence": 26,
      "event": "attempt-start",
      "node_type": "start",
      "timestamp": "2026-07-14T10:09:39.831644Z",
      "category": "attempt",
      "name": "xizi_double_link_init-annotation-r2-attempt-1",
      "phase": "annotation",
      "round": "xizi_double_link_init-annotation-r2",
      "group": null,
      "attempt": "xizi_double_link_init-annotation-r2-attempt-1",
      "timer_key": "attempt:xizi_double_link_init-annotation-r2-attempt-1"
    },
    {
      "sequence": 27,
      "event": "controller-command-end",
      "node_type": "end",
      "timestamp": "2026-07-14T10:09:39.833919Z",
      "category": "controller_command",
      "name": "mark-attempt-started",
      "phase": "annotation",
      "round": null,
      "group": null,
      "attempt": null,
      "timer_key": "controller_command:mark-attempt-started",
      "duration_seconds": 0.003105,
      "paired_start_sequence": 25
    },
    {
      "sequence": 28,
      "event": "controller-command-start",
      "node_type": "start",
      "timestamp": "2026-07-14T10:16:57.753700Z",
      "category": "controller_command",
      "name": "mark-attempt-returned",
      "phase": "annotation",
      "round": null,
      "group": null,
      "attempt": null,
      "timer_key": "controller_command:mark-attempt-returned"
    },
    {
      "sequence": 29,
      "event": "attempt-end",
      "node_type": "end",
      "timestamp": "2026-07-14T10:16:57.754566Z",
      "category": "attempt",
      "name": "xizi_double_link_init-annotation-r2-attempt-1",
      "phase": "annotation",
      "round": "xizi_double_link_init-annotation-r2",
      "group": null,
      "attempt": "xizi_double_link_init-annotation-r2-attempt-1",
      "timer_key": "attempt:xizi_double_link_init-annotation-r2-attempt-1",
      "duration_seconds": 437.922922,
      "paired_start_sequence": 26
    },
    {
      "sequence": 30,
      "event": "controller-command-end",
      "node_type": "end",
      "timestamp": "2026-07-14T10:16:57.756847Z",
      "category": "controller_command",
      "name": "mark-attempt-returned",
      "phase": "annotation",
      "round": null,
      "group": null,
      "attempt": null,
      "timer_key": "controller_command:mark-attempt-returned",
      "duration_seconds": 0.003147,
      "paired_start_sequence": 28
    },
    {
      "sequence": 31,
      "event": "controller-command-start",
      "node_type": "start",
      "timestamp": "2026-07-14T10:16:57.863413Z",
      "category": "controller_command",
      "name": "review-attempt",
      "phase": "annotation",
      "round": null,
      "group": null,
      "attempt": null,
      "timer_key": "controller_command:review-attempt"
    },
    {
      "sequence": 32,
      "event": "controller-command-end",
      "node_type": "end",
      "timestamp": "2026-07-14T10:16:57.866874Z",
      "category": "controller_command",
      "name": "review-attempt",
      "phase": "annotation",
      "round": null,
      "group": null,
      "attempt": null,
      "timer_key": "controller_command:review-attempt",
      "duration_seconds": 0.003461,
      "paired_start_sequence": 31
    },
    {
      "sequence": 33,
      "event": "controller-command-start",
      "node_type": "start",
      "timestamp": "2026-07-14T10:16:57.969061Z",
      "category": "controller_command",
      "name": "annotation-check-round",
      "phase": "annotation",
      "round": null,
      "group": null,
      "attempt": null,
      "timer_key": "controller_command:annotation-check-round"
    },
    {
      "sequence": 34,
      "event": "phase-end",
      "node_type": "end",
      "timestamp": "2026-07-14T10:16:57.981473Z",
      "category": "phase",
      "name": "annotation",
      "phase": "annotation",
      "round": null,
      "group": null,
      "attempt": null,
      "timer_key": "phase:annotation",
      "duration_seconds": 1415.240399,
      "paired_start_sequence": 7
    },
    {
      "sequence": 35,
      "event": "phase-start",
      "node_type": "start",
      "timestamp": "2026-07-14T10:16:57.981473Z",
      "category": "phase",
      "name": "vc-checking",
      "phase": "vc-checking",
      "round": null,
      "group": null,
      "attempt": null,
      "timer_key": "phase:vc-checking"
    },
    {
      "sequence": 36,
      "event": "controller-command-end",
      "node_type": "end",
      "timestamp": "2026-07-14T10:16:57.983669Z",
      "category": "controller_command",
      "name": "annotation-check-round",
      "phase": "vc-checking",
      "round": null,
      "group": null,
      "attempt": null,
      "timer_key": "controller_command:annotation-check-round",
      "duration_seconds": 0.014608,
      "paired_start_sequence": 33
    },
    {
      "sequence": 37,
      "event": "controller-command-start",
      "node_type": "start",
      "timestamp": "2026-07-14T10:17:05.565283Z",
      "category": "controller_command",
      "name": "step",
      "phase": "vc-checking",
      "round": null,
      "group": null,
      "attempt": null,
      "timer_key": "controller_command:step"
    },
    {
      "sequence": 38,
      "event": "controller-command-end",
      "node_type": "end",
      "timestamp": "2026-07-14T10:17:06.894533Z",
      "category": "controller_command",
      "name": "step",
      "phase": "vc-checking",
      "round": null,
      "group": null,
      "attempt": null,
      "timer_key": "controller_command:step",
      "duration_seconds": 1.32925,
      "paired_start_sequence": 37
    },
    {
      "sequence": 39,
      "event": "controller-command-start",
      "node_type": "start",
      "timestamp": "2026-07-14T10:17:06.988676Z",
      "category": "controller_command",
      "name": "spawn-instructions",
      "phase": "vc-checking",
      "round": null,
      "group": null,
      "attempt": null,
      "timer_key": "controller_command:spawn-instructions"
    },
    {
      "sequence": 40,
      "event": "controller-command-end",
      "node_type": "end",
      "timestamp": "2026-07-14T10:17:06.991196Z",
      "category": "controller_command",
      "name": "spawn-instructions",
      "phase": "vc-checking",
      "round": null,
      "group": null,
      "attempt": null,
      "timer_key": "controller_command:spawn-instructions",
      "duration_seconds": 0.00252,
      "paired_start_sequence": 39
    },
    {
      "sequence": 41,
      "event": "controller-command-start",
      "node_type": "start",
      "timestamp": "2026-07-14T10:17:28.227583Z",
      "category": "controller_command",
      "name": "mark-attempt-started",
      "phase": "vc-checking",
      "round": null,
      "group": null,
      "attempt": null,
      "timer_key": "controller_command:mark-attempt-started"
    },
    {
      "sequence": 42,
      "event": "attempt-start",
      "node_type": "start",
      "timestamp": "2026-07-14T10:17:28.228627Z",
      "category": "attempt",
      "name": "xizi_double_link_init-vc-checking-r1-attempt-1",
      "phase": "vc-checking",
      "round": "xizi_double_link_init-vc-checking-r1",
      "group": null,
      "attempt": "xizi_double_link_init-vc-checking-r1-attempt-1",
      "timer_key": "attempt:xizi_double_link_init-vc-checking-r1-attempt-1"
    },
    {
      "sequence": 43,
      "event": "controller-command-end",
      "node_type": "end",
      "timestamp": "2026-07-14T10:17:28.231320Z",
      "category": "controller_command",
      "name": "mark-attempt-started",
      "phase": "vc-checking",
      "round": null,
      "group": null,
      "attempt": null,
      "timer_key": "controller_command:mark-attempt-started",
      "duration_seconds": 0.003737,
      "paired_start_sequence": 41
    },
    {
      "sequence": 44,
      "event": "controller-command-start",
      "node_type": "start",
      "timestamp": "2026-07-14T10:21:08.029883Z",
      "category": "controller_command",
      "name": "mark-attempt-returned",
      "phase": "vc-checking",
      "round": null,
      "group": null,
      "attempt": null,
      "timer_key": "controller_command:mark-attempt-returned"
    },
    {
      "sequence": 45,
      "event": "attempt-end",
      "node_type": "end",
      "timestamp": "2026-07-14T10:21:08.031038Z",
      "category": "attempt",
      "name": "xizi_double_link_init-vc-checking-r1-attempt-1",
      "phase": "vc-checking",
      "round": "xizi_double_link_init-vc-checking-r1",
      "group": null,
      "attempt": "xizi_double_link_init-vc-checking-r1-attempt-1",
      "timer_key": "attempt:xizi_double_link_init-vc-checking-r1-attempt-1",
      "duration_seconds": 219.802411,
      "paired_start_sequence": 42
    },
    {
      "sequence": 46,
      "event": "controller-command-end",
      "node_type": "end",
      "timestamp": "2026-07-14T10:21:08.033716Z",
      "category": "controller_command",
      "name": "mark-attempt-returned",
      "phase": "vc-checking",
      "round": null,
      "group": null,
      "attempt": null,
      "timer_key": "controller_command:mark-attempt-returned",
      "duration_seconds": 0.003833,
      "paired_start_sequence": 44
    },
    {
      "sequence": 47,
      "event": "controller-command-start",
      "node_type": "start",
      "timestamp": "2026-07-14T10:21:08.144636Z",
      "category": "controller_command",
      "name": "review-attempt",
      "phase": "vc-checking",
      "round": null,
      "group": null,
      "attempt": null,
      "timer_key": "controller_command:review-attempt"
    },
    {
      "sequence": 48,
      "event": "controller-command-end",
      "node_type": "end",
      "timestamp": "2026-07-14T10:21:08.148343Z",
      "category": "controller_command",
      "name": "review-attempt",
      "phase": "vc-checking",
      "round": null,
      "group": null,
      "attempt": null,
      "timer_key": "controller_command:review-attempt",
      "duration_seconds": 0.003707,
      "paired_start_sequence": 47
    },
    {
      "sequence": 49,
      "event": "controller-command-start",
      "node_type": "start",
      "timestamp": "2026-07-14T10:21:40.019032Z",
      "category": "controller_command",
      "name": "retry-round",
      "phase": "vc-checking",
      "round": null,
      "group": null,
      "attempt": null,
      "timer_key": "controller_command:retry-round"
    },
    {
      "sequence": 50,
      "event": "controller-command-end",
      "node_type": "end",
      "timestamp": "2026-07-14T10:21:41.394770Z",
      "category": "controller_command",
      "name": "retry-round",
      "phase": "vc-checking",
      "round": null,
      "group": null,
      "attempt": null,
      "timer_key": "controller_command:retry-round",
      "duration_seconds": 1.375738,
      "paired_start_sequence": 49
    },
    {
      "sequence": 51,
      "event": "controller-command-start",
      "node_type": "start",
      "timestamp": "2026-07-14T10:21:48.985508Z",
      "category": "controller_command",
      "name": "spawn-instructions",
      "phase": "vc-checking",
      "round": null,
      "group": null,
      "attempt": null,
      "timer_key": "controller_command:spawn-instructions"
    },
    {
      "sequence": 52,
      "event": "controller-command-end",
      "node_type": "end",
      "timestamp": "2026-07-14T10:21:48.988511Z",
      "category": "controller_command",
      "name": "spawn-instructions",
      "phase": "vc-checking",
      "round": null,
      "group": null,
      "attempt": null,
      "timer_key": "controller_command:spawn-instructions",
      "duration_seconds": 0.003003,
      "paired_start_sequence": 51
    },
    {
      "sequence": 53,
      "event": "controller-command-start",
      "node_type": "start",
      "timestamp": "2026-07-14T10:22:48.305992Z",
      "category": "controller_command",
      "name": "mark-attempt-started",
      "phase": "vc-checking",
      "round": null,
      "group": null,
      "attempt": null,
      "timer_key": "controller_command:mark-attempt-started"
    },
    {
      "sequence": 54,
      "event": "attempt-start",
      "node_type": "start",
      "timestamp": "2026-07-14T10:22:48.307354Z",
      "category": "attempt",
      "name": "xizi_double_link_init-vc-checking-r2-attempt-1",
      "phase": "vc-checking",
      "round": "xizi_double_link_init-vc-checking-r2",
      "group": null,
      "attempt": "xizi_double_link_init-vc-checking-r2-attempt-1",
      "timer_key": "attempt:xizi_double_link_init-vc-checking-r2-attempt-1"
    },
    {
      "sequence": 55,
      "event": "controller-command-end",
      "node_type": "end",
      "timestamp": "2026-07-14T10:22:48.310578Z",
      "category": "controller_command",
      "name": "mark-attempt-started",
      "phase": "vc-checking",
      "round": null,
      "group": null,
      "attempt": null,
      "timer_key": "controller_command:mark-attempt-started",
      "duration_seconds": 0.004586,
      "paired_start_sequence": 53
    },
    {
      "sequence": 56,
      "event": "controller-command-start",
      "node_type": "start",
      "timestamp": "2026-07-14T10:24:11.131996Z",
      "category": "controller_command",
      "name": "mark-attempt-returned",
      "phase": "vc-checking",
      "round": null,
      "group": null,
      "attempt": null,
      "timer_key": "controller_command:mark-attempt-returned"
    },
    {
      "sequence": 57,
      "event": "attempt-end",
      "node_type": "end",
      "timestamp": "2026-07-14T10:24:11.133699Z",
      "category": "attempt",
      "name": "xizi_double_link_init-vc-checking-r2-attempt-1",
      "phase": "vc-checking",
      "round": "xizi_double_link_init-vc-checking-r2",
      "group": null,
      "attempt": "xizi_double_link_init-vc-checking-r2-attempt-1",
      "timer_key": "attempt:xizi_double_link_init-vc-checking-r2-attempt-1",
      "duration_seconds": 82.826345,
      "paired_start_sequence": 54
    },
    {
      "sequence": 58,
      "event": "controller-command-end",
      "node_type": "end",
      "timestamp": "2026-07-14T10:24:11.137006Z",
      "category": "controller_command",
      "name": "mark-attempt-returned",
      "phase": "vc-checking",
      "round": null,
      "group": null,
      "attempt": null,
      "timer_key": "controller_command:mark-attempt-returned",
      "duration_seconds": 0.00501,
      "paired_start_sequence": 56
    },
    {
      "sequence": 59,
      "event": "controller-command-start",
      "node_type": "start",
      "timestamp": "2026-07-14T10:24:11.244128Z",
      "category": "controller_command",
      "name": "review-attempt",
      "phase": "vc-checking",
      "round": null,
      "group": null,
      "attempt": null,
      "timer_key": "controller_command:review-attempt"
    },
    {
      "sequence": 60,
      "event": "controller-command-end",
      "node_type": "end",
      "timestamp": "2026-07-14T10:24:11.249141Z",
      "category": "controller_command",
      "name": "review-attempt",
      "phase": "vc-checking",
      "round": null,
      "group": null,
      "attempt": null,
      "timer_key": "controller_command:review-attempt",
      "duration_seconds": 0.005013,
      "paired_start_sequence": 59
    },
    {
      "sequence": 61,
      "event": "controller-command-start",
      "node_type": "start",
      "timestamp": "2026-07-14T10:24:11.364832Z",
      "category": "controller_command",
      "name": "vc-checking-check-round",
      "phase": "vc-checking",
      "round": null,
      "group": null,
      "attempt": null,
      "timer_key": "controller_command:vc-checking-check-round"
    },
    {
      "sequence": 62,
      "event": "controller-command-end",
      "node_type": "end",
      "timestamp": "2026-07-14T10:24:11.368013Z",
      "category": "controller_command",
      "name": "vc-checking-check-round",
      "phase": "vc-checking",
      "round": null,
      "group": null,
      "attempt": null,
      "timer_key": "controller_command:vc-checking-check-round",
      "duration_seconds": 0.003181,
      "paired_start_sequence": 61
    },
    {
      "sequence": 63,
      "event": "controller-command-start",
      "node_type": "start",
      "timestamp": "2026-07-14T10:25:12.875806Z",
      "category": "controller_command",
      "name": "vc-checking-check-round",
      "phase": "vc-checking",
      "round": null,
      "group": null,
      "attempt": null,
      "timer_key": "controller_command:vc-checking-check-round"
    },
    {
      "sequence": 64,
      "event": "phase-end",
      "node_type": "end",
      "timestamp": "2026-07-14T10:25:12.878962Z",
      "category": "phase",
      "name": "vc-checking",
      "phase": "vc-checking",
      "round": null,
      "group": null,
      "attempt": null,
      "timer_key": "phase:vc-checking",
      "duration_seconds": 494.897489,
      "paired_start_sequence": 35
    },
    {
      "sequence": 65,
      "event": "phase-start",
      "node_type": "start",
      "timestamp": "2026-07-14T10:25:12.878962Z",
      "category": "phase",
      "name": "vc-proving-preparing",
      "phase": "vc-proving-preparing",
      "round": null,
      "group": null,
      "attempt": null,
      "timer_key": "phase:vc-proving-preparing"
    },
    {
      "sequence": 66,
      "event": "controller-command-end",
      "node_type": "end",
      "timestamp": "2026-07-14T10:25:12.882369Z",
      "category": "controller_command",
      "name": "vc-checking-check-round",
      "phase": "vc-proving-preparing",
      "round": null,
      "group": null,
      "attempt": null,
      "timer_key": "controller_command:vc-checking-check-round",
      "duration_seconds": 0.006563,
      "paired_start_sequence": 63
    },
    {
      "sequence": 67,
      "event": "controller-command-start",
      "node_type": "start",
      "timestamp": "2026-07-14T10:25:28.209279Z",
      "category": "controller_command",
      "name": "step",
      "phase": "vc-proving-preparing",
      "round": null,
      "group": null,
      "attempt": null,
      "timer_key": "controller_command:step"
    },
    {
      "sequence": 68,
      "event": "controller-command-end",
      "node_type": "end",
      "timestamp": "2026-07-14T10:25:28.214456Z",
      "category": "controller_command",
      "name": "step",
      "phase": "vc-proving-preparing",
      "round": null,
      "group": null,
      "attempt": null,
      "timer_key": "controller_command:step",
      "duration_seconds": 0.005177,
      "paired_start_sequence": 67
    },
    {
      "sequence": 69,
      "event": "controller-command-start",
      "node_type": "start",
      "timestamp": "2026-07-14T10:25:32.149810Z",
      "category": "controller_command",
      "name": "vc-proving-preparing",
      "phase": "vc-proving-preparing",
      "round": null,
      "group": null,
      "attempt": null,
      "timer_key": "controller_command:vc-proving-preparing"
    },
    {
      "sequence": 70,
      "event": "controller-command-end",
      "node_type": "end",
      "timestamp": "2026-07-14T10:25:33.835361Z",
      "category": "controller_command",
      "name": "vc-proving-preparing",
      "phase": "vc-proving-preparing",
      "round": null,
      "group": null,
      "attempt": null,
      "timer_key": "controller_command:vc-proving-preparing",
      "duration_seconds": 1.685551,
      "paired_start_sequence": 69
    },
    {
      "sequence": 71,
      "event": "controller-command-start",
      "node_type": "start",
      "timestamp": "2026-07-14T10:33:00.326778Z",
      "category": "controller_command",
      "name": "review-attempt",
      "phase": "vc-proving-preparing",
      "round": null,
      "group": null,
      "attempt": null,
      "timer_key": "controller_command:review-attempt"
    },
    {
      "sequence": 72,
      "event": "controller-command-end",
      "node_type": "end",
      "timestamp": "2026-07-14T10:33:00.334212Z",
      "category": "controller_command",
      "name": "review-attempt",
      "phase": "vc-proving-preparing",
      "round": null,
      "group": null,
      "attempt": null,
      "timer_key": "controller_command:review-attempt",
      "duration_seconds": 0.007434,
      "paired_start_sequence": 71
    },
    {
      "sequence": 73,
      "event": "controller-command-start",
      "node_type": "start",
      "timestamp": "2026-07-14T10:33:00.441740Z",
      "category": "controller_command",
      "name": "vc-proving-verify",
      "phase": "vc-proving-preparing",
      "round": null,
      "group": null,
      "attempt": null,
      "timer_key": "controller_command:vc-proving-verify"
    },
    {
      "sequence": 74,
      "event": "controller-command-start",
      "node_type": "start",
      "timestamp": "2026-07-14T10:34:27.644476Z",
      "category": "controller_command",
      "name": "vc-proving-verify",
      "phase": "vc-proving-preparing",
      "round": null,
      "group": null,
      "attempt": null,
      "timer_key": "controller_command:vc-proving-verify"
    },
    {
      "sequence": 75,
      "event": "phase-end",
      "node_type": "end",
      "timestamp": "2026-07-14T10:35:24.848430Z",
      "category": "phase",
      "name": "vc-proving-preparing",
      "phase": "vc-proving-preparing",
      "round": null,
      "group": null,
      "attempt": null,
      "timer_key": "phase:vc-proving-preparing",
      "duration_seconds": 611.969468,
      "paired_start_sequence": 65
    },
    {
      "sequence": 76,
      "event": "phase-start",
      "node_type": "start",
      "timestamp": "2026-07-14T10:35:24.848430Z",
      "category": "phase",
      "name": "final-check",
      "phase": "final-check",
      "round": null,
      "group": null,
      "attempt": null,
      "timer_key": "phase:final-check"
    },
    {
      "sequence": 77,
      "event": "controller-command-end",
      "node_type": "end",
      "timestamp": "2026-07-14T10:35:24.857522Z",
      "category": "controller_command",
      "name": "vc-proving-verify",
      "phase": "final-check",
      "round": null,
      "group": null,
      "attempt": null,
      "timer_key": "controller_command:vc-proving-verify",
      "duration_seconds": 57.213046,
      "paired_start_sequence": 74
    },
    {
      "sequence": 78,
      "event": "phase-end",
      "node_type": "end",
      "timestamp": "2026-07-14T10:36:44.411835Z",
      "category": "phase",
      "name": "vc-proving-preparing",
      "phase": "vc-proving-preparing",
      "round": null,
      "group": null,
      "attempt": null,
      "timer_key": "phase:vc-proving-preparing"
    },
    {
      "sequence": 79,
      "event": "phase-start",
      "node_type": "start",
      "timestamp": "2026-07-14T10:36:44.411835Z",
      "category": "phase",
      "name": "final-check",
      "phase": "final-check",
      "round": null,
      "group": null,
      "attempt": null,
      "timer_key": "phase:final-check"
    },
    {
      "sequence": 80,
      "event": "controller-command-end",
      "node_type": "end",
      "timestamp": "2026-07-14T10:36:44.416256Z",
      "category": "controller_command",
      "name": "vc-proving-verify",
      "phase": "final-check",
      "round": null,
      "group": null,
      "attempt": null,
      "timer_key": "controller_command:vc-proving-verify",
      "duration_seconds": 223.974516,
      "paired_start_sequence": 73
    },
    {
      "sequence": 81,
      "event": "controller-command-start",
      "node_type": "start",
      "timestamp": "2026-07-14T10:36:49.162955Z",
      "category": "controller_command",
      "name": "step",
      "phase": "final-check",
      "round": null,
      "group": null,
      "attempt": null,
      "timer_key": "controller_command:step"
    },
    {
      "sequence": 82,
      "event": "controller-command-end",
      "node_type": "end",
      "timestamp": "2026-07-14T10:36:49.166527Z",
      "category": "controller_command",
      "name": "step",
      "phase": "final-check",
      "round": null,
      "group": null,
      "attempt": null,
      "timer_key": "controller_command:step",
      "duration_seconds": 0.003572,
      "paired_start_sequence": 81
    },
    {
      "sequence": 83,
      "event": "controller-command-start",
      "node_type": "start",
      "timestamp": "2026-07-14T10:37:16.219633Z",
      "category": "controller_command",
      "name": "final-apply",
      "phase": "final-check",
      "round": null,
      "group": null,
      "attempt": null,
      "timer_key": "controller_command:final-apply"
    },
    {
      "sequence": 84,
      "event": "controller-command-end",
      "node_type": "end",
      "timestamp": "2026-07-14T10:37:16.233044Z",
      "category": "controller_command",
      "name": "final-apply",
      "phase": "final-check",
      "round": null,
      "group": null,
      "attempt": null,
      "timer_key": "controller_command:final-apply",
      "duration_seconds": 0.013411,
      "paired_start_sequence": 83
    },
    {
      "sequence": 85,
      "event": "controller-command-start",
      "node_type": "start",
      "timestamp": "2026-07-14T10:37:22.617225Z",
      "category": "controller_command",
      "name": "final-check",
      "phase": "final-check",
      "round": null,
      "group": null,
      "attempt": null,
      "timer_key": "controller_command:final-check"
    },
    {
      "sequence": 86,
      "event": "phase-end",
      "node_type": "end",
      "timestamp": "2026-07-14T10:39:35.051151Z",
      "category": "phase",
      "name": "final-check",
      "phase": "final-check",
      "round": null,
      "group": null,
      "attempt": null,
      "timer_key": "phase:final-check",
      "duration_seconds": 170.639316,
      "paired_start_sequence": 79
    },
    {
      "sequence": 87,
      "event": "run-end",
      "node_type": "end",
      "timestamp": "2026-07-14T10:39:35.051151Z",
      "category": "run",
      "name": "xizi_double_link_init-20260714180003",
      "phase": "done",
      "round": null,
      "group": null,
      "attempt": null,
      "timer_key": "run:xizi_double_link_init-20260714180003",
      "duration_seconds": 2786.079568,
      "paired_start_sequence": 2
    },
    {
      "sequence": 88,
      "event": "controller-command-end",
      "node_type": "end",
      "timestamp": "2026-07-14T10:39:35.057321Z",
      "category": "controller_command",
      "name": "final-check",
      "phase": "done",
      "round": null,
      "group": null,
      "attempt": null,
      "timer_key": "controller_command:final-check",
      "duration_seconds": 132.440096,
      "paired_start_sequence": 85
    }
  ],
  "duration_summary": {
    "closed_interval_count": 43,
    "categories": {
      "controller_command": {
        "init-run": {
          "count": 1,
          "total_seconds": 0.004833,
          "first_started_at": "2026-07-14T09:53:08.971583Z",
          "last_ended_at": "2026-07-14T09:53:08.976416Z",
          "last_duration_seconds": 0.004833
        },
        "step": {
          "count": 4,
          "total_seconds": 2.610626,
          "first_started_at": "2026-07-14T09:53:21.482870Z",
          "last_ended_at": "2026-07-14T10:36:49.166527Z",
          "last_duration_seconds": 0.003572
        },
        "spawn-instructions": {
          "count": 4,
          "total_seconds": 0.009098,
          "first_started_at": "2026-07-14T09:53:28.947690Z",
          "last_ended_at": "2026-07-14T10:21:48.988511Z",
          "last_duration_seconds": 0.003003
        },
        "mark-attempt-started": {
          "count": 4,
          "total_seconds": 0.013966,
          "first_started_at": "2026-07-14T09:54:11.110622Z",
          "last_ended_at": "2026-07-14T10:22:48.310578Z",
          "last_duration_seconds": 0.004586
        },
        "mark-attempt-returned": {
          "count": 4,
          "total_seconds": 0.014537,
          "first_started_at": "2026-07-14T10:08:59.125529Z",
          "last_ended_at": "2026-07-14T10:24:11.137006Z",
          "last_duration_seconds": 0.00501
        },
        "review-attempt": {
          "count": 5,
          "total_seconds": 0.022486,
          "first_started_at": "2026-07-14T10:08:59.237399Z",
          "last_ended_at": "2026-07-14T10:33:00.334212Z",
          "last_duration_seconds": 0.007434
        },
        "retry-round": {
          "count": 3,
          "total_seconds": 2.690331,
          "first_started_at": "2026-07-14T10:09:08.220487Z",
          "last_ended_at": "2026-07-14T10:21:41.394770Z",
          "last_duration_seconds": 1.375738
        },
        "annotation-check-round": {
          "count": 1,
          "total_seconds": 0.014608,
          "first_started_at": "2026-07-14T10:16:57.969061Z",
          "last_ended_at": "2026-07-14T10:16:57.983669Z",
          "last_duration_seconds": 0.014608
        },
        "vc-checking-check-round": {
          "count": 2,
          "total_seconds": 0.009744,
          "first_started_at": "2026-07-14T10:24:11.364832Z",
          "last_ended_at": "2026-07-14T10:25:12.882369Z",
          "last_duration_seconds": 0.006563
        },
        "vc-proving-preparing": {
          "count": 1,
          "total_seconds": 1.685551,
          "first_started_at": "2026-07-14T10:25:32.149810Z",
          "last_ended_at": "2026-07-14T10:25:33.835361Z",
          "last_duration_seconds": 1.685551
        },
        "vc-proving-verify": {
          "count": 2,
          "total_seconds": 281.187562,
          "first_started_at": "2026-07-14T10:34:27.644476Z",
          "last_ended_at": "2026-07-14T10:36:44.416256Z",
          "last_duration_seconds": 223.974516
        },
        "final-apply": {
          "count": 1,
          "total_seconds": 0.013411,
          "first_started_at": "2026-07-14T10:37:16.219633Z",
          "last_ended_at": "2026-07-14T10:37:16.233044Z",
          "last_duration_seconds": 0.013411
        },
        "final-check": {
          "count": 1,
          "total_seconds": 132.440096,
          "first_started_at": "2026-07-14T10:37:22.617225Z",
          "last_ended_at": "2026-07-14T10:39:35.057321Z",
          "last_duration_seconds": 132.440096
        }
      },
      "phase": {
        "intake": {
          "count": 1,
          "total_seconds": 13.769491,
          "first_started_at": "2026-07-14T09:53:08.971583Z",
          "last_ended_at": "2026-07-14T09:53:22.741074Z",
          "last_duration_seconds": 13.769491
        },
        "annotation": {
          "count": 1,
          "total_seconds": 1415.240399,
          "first_started_at": "2026-07-14T09:53:22.741074Z",
          "last_ended_at": "2026-07-14T10:16:57.981473Z",
          "last_duration_seconds": 1415.240399
        },
        "vc-checking": {
          "count": 1,
          "total_seconds": 494.897489,
          "first_started_at": "2026-07-14T10:16:57.981473Z",
          "last_ended_at": "2026-07-14T10:25:12.878962Z",
          "last_duration_seconds": 494.897489
        },
        "vc-proving-preparing": {
          "count": 1,
          "total_seconds": 611.969468,
          "first_started_at": "2026-07-14T10:25:12.878962Z",
          "last_ended_at": "2026-07-14T10:35:24.848430Z",
          "last_duration_seconds": 611.969468
        },
        "final-check": {
          "count": 1,
          "total_seconds": 170.639316,
          "first_started_at": "2026-07-14T10:36:44.411835Z",
          "last_ended_at": "2026-07-14T10:39:35.051151Z",
          "last_duration_seconds": 170.639316
        }
      },
      "attempt": {
        "xizi_double_link_init-annotation-r1-attempt-1": {
          "count": 1,
          "total_seconds": 888.01485,
          "first_started_at": "2026-07-14T09:54:11.111305Z",
          "last_ended_at": "2026-07-14T10:08:59.126155Z",
          "last_duration_seconds": 888.01485
        },
        "xizi_double_link_init-annotation-r2-attempt-1": {
          "count": 1,
          "total_seconds": 437.922922,
          "first_started_at": "2026-07-14T10:09:39.831644Z",
          "last_ended_at": "2026-07-14T10:16:57.754566Z",
          "last_duration_seconds": 437.922922
        },
        "xizi_double_link_init-vc-checking-r1-attempt-1": {
          "count": 1,
          "total_seconds": 219.802411,
          "first_started_at": "2026-07-14T10:17:28.228627Z",
          "last_ended_at": "2026-07-14T10:21:08.031038Z",
          "last_duration_seconds": 219.802411
        },
        "xizi_double_link_init-vc-checking-r2-attempt-1": {
          "count": 1,
          "total_seconds": 82.826345,
          "first_started_at": "2026-07-14T10:22:48.307354Z",
          "last_ended_at": "2026-07-14T10:24:11.133699Z",
          "last_duration_seconds": 82.826345
        }
      },
      "run": {
        "xizi_double_link_init-20260714180003": {
          "count": 1,
          "total_seconds": 2786.079568,
          "first_started_at": "2026-07-14T09:53:08.971583Z",
          "last_ended_at": "2026-07-14T10:39:35.051151Z",
          "last_duration_seconds": 2786.079568
        }
      }
    }
  },
  "phase_time": {
    "intake": {
      "count": 1,
      "total_seconds": 13.769491,
      "first_started_at": "2026-07-14T09:53:08.971583Z",
      "last_ended_at": "2026-07-14T09:53:22.741074Z",
      "last_duration_seconds": 13.769491
    },
    "annotation": {
      "count": 1,
      "total_seconds": 1415.240399,
      "first_started_at": "2026-07-14T09:53:22.741074Z",
      "last_ended_at": "2026-07-14T10:16:57.981473Z",
      "last_duration_seconds": 1415.240399
    },
    "vc-checking": {
      "count": 1,
      "total_seconds": 494.897489,
      "first_started_at": "2026-07-14T10:16:57.981473Z",
      "last_ended_at": "2026-07-14T10:25:12.878962Z",
      "last_duration_seconds": 494.897489
    },
    "vc-proving-preparing": {
      "count": 1,
      "total_seconds": 611.969468,
      "first_started_at": "2026-07-14T10:25:12.878962Z",
      "last_ended_at": "2026-07-14T10:35:24.848430Z",
      "last_duration_seconds": 611.969468
    },
    "final-check": {
      "count": 1,
      "total_seconds": 170.639316,
      "first_started_at": "2026-07-14T10:36:44.411835Z",
      "last_ended_at": "2026-07-14T10:39:35.051151Z",
      "last_duration_seconds": 170.639316
    }
  },
  "worker_time": {
    "xizi_double_link_init-annotation-r1-attempt-1": {
      "count": 1,
      "total_seconds": 888.01485,
      "first_started_at": "2026-07-14T09:54:11.111305Z",
      "last_ended_at": "2026-07-14T10:08:59.126155Z",
      "last_duration_seconds": 888.01485
    },
    "xizi_double_link_init-annotation-r2-attempt-1": {
      "count": 1,
      "total_seconds": 437.922922,
      "first_started_at": "2026-07-14T10:09:39.831644Z",
      "last_ended_at": "2026-07-14T10:16:57.754566Z",
      "last_duration_seconds": 437.922922
    },
    "xizi_double_link_init-vc-checking-r1-attempt-1": {
      "count": 1,
      "total_seconds": 219.802411,
      "first_started_at": "2026-07-14T10:17:28.228627Z",
      "last_ended_at": "2026-07-14T10:21:08.031038Z",
      "last_duration_seconds": 219.802411
    },
    "xizi_double_link_init-vc-checking-r2-attempt-1": {
      "count": 1,
      "total_seconds": 82.826345,
      "first_started_at": "2026-07-14T10:22:48.307354Z",
      "last_ended_at": "2026-07-14T10:24:11.133699Z",
      "last_duration_seconds": 82.826345
    }
  },
  "coq_time": {},
  "retry_reasons": {},
  "compact_counts": {},
  "stale_lost_time": {}
}
